{
  "pages": [
    {
      "Name": "Applicant",
      "Enabled": true,
      "Actions": [
        {
          "action": "navigate",
          "args": [ "https://hh.serviceconnector.osp.dataport.de/HamburgGateway-dev-ci", "" ]
        },
        {
          "action": "clickbytext",
          "args": [ "Weitere", "" ]
        },
        {
          "action": "clickbytext",
          "args": [ "Weitere", "" ]
        },
        {
          "action": "clickbypath",
          "args": [ "//*[@id=\"sc-all-services\"]/ul/li[7]", "" ]
        },
        {
          "action": "clickbytext",
          "args": [ "Anmelden", "" ]
        },
        {
          "action": "clickbycss",
          "args": [
            "input[value='setinputgn In']",
            ""
          ]
        },
        {
          "action": "clickbytext",
          "args": [ "Hier starten", "" ]
        },
        {
          "action": "clickbycss",
          "args": [ "input[value='setinputgn In']", "" ]
        },
        {
          "action": "setinput",
          "args": [ "BSPostalCode", "24620, Bönebüttel, Gemeinde Bönebüttel" ]
        },
        {
          "action": "click",
          "args": [ "buttonNext", "" ]
        },
        {
          "action": "click",
          "args": [ "DSGVOCheckbox_label", "" ]
        },
        {
          "action": "click",
          "args": [ "buttonNext", "" ]
        },
        {
          "action": "setinput",
          "args": [ "ADAICAReferenceNumber", "Gemeinde Bönebüttel" ]
        },
        {
          "action": "click",
          "args": [ "buttonNext", "" ]
        }

      ]
    },
    {
      "Name": "Housetinputng",
      "Enabled": true,
      "Actions": [
        {
          "action": "click",
          "args": [ "SumCardHousetinputngAllowanceRequestApplicant_link", "" ]
        },
        {
          "action": "setdropdown",
          "args": [ "DropdownListARepresentation", "01" ]
        },
        {
          "action": "click",
          "args": [ "Wizard_WizardItemALRA_nextButton", "01" ]
        },
        {
          "action": "setinput",
          "args": [ "ADABirthPlace", "24620, Bönebüttel, Gemeinde Bönebüttel" ]
        },
        {
          "action": "setdropdown",
          "args": [ "ADACivilStatus", "006" ]
        },
        {
          "action": "setdropdown",
          "args": [ "ADAEmploymentStatus", "001" ]
        },
        {
          "action": "setdropdown",
          "args": [ "ADACitizenshipCard_0__ADACitizenship", "998" ]
        },
        {
          "action": "click",
          "args": [ "Wizard_WizardItemApplicantDetails_nextButton", "" ]
        },
        {
          "action": "setdropdown",
          "args": [ "ADATransferBenefitsQuestionReception", "01" ]
        },
        {
          "action": "setdropdown",
          "args": [ "ADATransferBenefitsRequestQuestion", "01" ]
        },
        {
          "action": "click",
          "args": [ "Wizard_ADATransferBenefits_nextButton", "" ]
        },
        {
          "action": "setdropdown",
          "args": [ "ADAIncomeQuestion1", "01" ]
        },
        {
          "action": "click",
          "args": [ "Wizard_ADAIncome_nextButton", "01" ]
        },
        {
          "action": "setdropdown",
          "args": [ "ADACCQuestion", "01" ]
        },
        {
          "action": "click",
          "args": [ "Wizard_ADAChildCareExpenses_nextButton", "" ]
        },
        {
          "action": "setdropdown",
          "args": [ "ADADQuestion", "01" ]
        },
        {
          "action": "click",
          "args": [ "Wizard_ADADisability_nextButton", "" ]
        },
        {
          "action": "setdropdown",
          "args": [ "ADAVNSPQuestion", "01" ]
        },
        {
          "action": "click",
          "args": [ "Wizard_ADAVictimNSPersecution_nextButton", "01" ]
        },
        {
          "action": "setdropdown",
          "args": [ "ADAAPQuestion", "01" ]
        },
        {
          "action": "click",
          "args": [ "Wizard_ADAAlimonyPayment_nextButton", "01" ]
        },
        {
          "action": "setdropdown",
          "args": [ "ADAACQuestion", "01" ]
        },
        {
          "action": "click",
          "args": [ "Wizard_ADAAlimonyClaim_nextButton", "" ]
        },
        {
          "action": "setdropdown",
          "args": [ "ADAOIQuestion", "01" ]
        },
        {
          "action": "click",
          "args": [ "Wizard_ADAOnetimeIncome_nextButton", "" ]
        },
        {
          "action": "setdropdown",
          "args": [ "AHMQuestion", "01" ]
        },
        {
          "action": "click",
          "args": [ "Wizard_WizardItemAdditionalHM_nextButton", "" ]
        },
        {
          "action": "setdropdown",
          "args": [ "ADCQuestionCommitment", "01" ]
        },
        {
          "action": "click",
          "args": [ "Wizard_WizardItemDoC_nextButton", "" ]
        },
        {
          "action": "setdropdown",
          "args": [ "ADAAssetsQuestion", "01" ]
        },
        {
          "action": "click",
          "args": [ "Wizard_ADAAssets_nextButton", "" ]
        }



      ]
    },
    {
      "Name": "HHMember",
      "Enabled": true,
      "Actions": [
        {
          "action": "click",
          "args": [ "SumCardHousetinputngAllowanceRequestYourApartment_link", "" ]
        },
        {
          "action": "setinput",
          "args": [ "YHAAStreet", "Bönebüttel" ]
        },
        {
          "action": "setinput",
          "args": [ "YHAAPostalCode", "11111" ]
        },
        {
          "action": "setinput",
          "args": [ "YHAACity", "11111" ]
        },
        {
          "action": "click",
          "args": [ "YHAAActualHousetinputng_0__Selected_radioButton_label", "" ]
        },
        {
          "action": "click",
          "args": [ "Wizard_HousetinputngAddress_nextButton", "" ]
        },
        {
          "action": "setdropdown",
          "args": [ "YHOAQuestion", "01" ]
        },
        {
          "action": "click",
          "args": [ "Wizard_HAOtherApartment_nextButton", "" ]
        },
        {
          "action": "setdropdown",
          "args": [ "YHPAQuestion", "01" ]
        },
        {
          "action": "click",
          "args": [ "Wizard_HousetinputngSocialContribution_nextButton", "" ]
        },
        {
          "action": "setdropdown",
          "args": [ "YHDQuestion", "01" ]
        },
        {
          "action": "click",
          "args": [ "Wizard_HousetinputngDecease_nextButton", "" ]
        },
        {
          "action": "setdropdown",
          "args": [ "YHPHMQuestion", "01" ]
        },
        {
          "action": "click",
          "args": [ "Wizard_HousetinputngProspectiveHM_nextButton", "" ]
        },
        {
          "action": "setdropdown",
          "args": [ "YHRQuestion", "01" ]
        },
        {
          "action": "click",
          "args": [ "Wizard_HousetinputngRelocation_nextButton", "" ]
        },
        {
          "action": "setdropdown",
          "args": [ "YHTRTenancyQuestion", "004" ]
        },
        {
          "action": "setdropdown",
          "args": [ "YHTRRelationshipQuestion", "01" ]
        },
        {
          "action": "click",
          "args": [ "Wizard_HousetinputngTenancyRelationship_nextButton", "" ]
        },
        {
          "action": "setdropdown",
          "args": [ "YHASsetinputzeQuestion", "02" ]
        },
        {
          "action": "click",
          "args": [ "Wizard_HousetinputngApartmentsetinputze_nextButton", "" ]
        },
        {
          "action": "setinput",
          "args": [ "YHCRent", "12,12" ]
        },
        {
          "action": "setdropdown",
          "args": [ "YHCHeatingCostsQuestion", "02" ]
        },
        {
          "action": "setdropdown",
          "args": [ "YHCHotWaterCostsQuestion", "02" ]
        },
        {
          "action": "setdropdown",
          "args": [ "YHCGarageCostsQuestion", "02" ]
        },
        {
          "action": "setdropdown",
          "args": [ "YHCCarportCostsQuestion", "02" ]
        },
        {
          "action": "setdropdown",
          "args": [ "YHCFixedRateQuestion", "02" ]
        },
        {
          "action": "setdropdown",
          "args": [ "YHCECLandlordQuestion", "02" ]
        },
        {
          "action": "setdropdown",
          "args": [ "YHCThirdPartiesQuestion", "02" ]
        },
        {
          "action": "setinput",
          "args": [ "YHCThirdParties", "12,12" ]
        },
        {
          "action": "click",
          "args": [ "Wizard_HousetinputngCharges_nextButton", "" ]
        },
        {
          "action": "setdropdown",
          "args": [ "YHARAllowanceQuestion", "03" ]
        },
        {
          "action": "setdropdown",
          "args": [ "YHARReductionQuestion", "03" ]
        },
        {
          "action": "up",
          "args": [
            "YHARDocumentUpload",
            "C:/Users/developer/downloads/Hans-Peter_Buerger_Lastenzuschuss_Erstantrag_20221110(4).pdf"
          ]
        },
        {
          "action": "setdropdown",
          "args": [ "YHARReductionQuestion", "03" ]
        },
        {
          "action": "setdropdown",
          "args": [ "YHARAllowanceQuestion", "03" ]
        },
        {
          "action": "click",
          "args": [ "Wizard_HousetinputngAllowanceReduction_nextButton", "" ]
        },
        {
          "action": "setinput",
          "args": [ "YHHCOtherUsageOfHousetinputngsetinputze", "12,12" ]
        },
        {
          "action": "setdropdown",
          "args": [ "YHHCOtherUsageOfHousetinputngRoomyQuestion", "01" ]
        },
        {
          "action": "click",
          "args": [ "Wizard_YHHCOtherUsageOfHousetinputng_nextButton", "" ]
        }

      ]
    },
    {
      "Name": "CompleteApplication",
      "Enabled": true,
      "Actions": [
        {
          "action": "click",
          "args": [ "SumCardHousetinputngAllowanceRequestCompleteApplication_link", "" ]
        },
        {
          "action": "setdropdown",
          "args": [ "EAQPRecipientDropdownOne", "001" ]
        },
        {
          "action": "click",
          "args": [ "EAQPBankAccountRadioButton_1__Selected_radioButton_label", "" ]
        },
        {
          "action": "click",
          "args": [ "Wizard_EAQPQuestionsAboutPayment_nextButton", "" ]
        },
        {
          "action": "click",
          "args": [ "Wizard_EAMessageFromApplicant_nextButton", "" ]
        },
        {
          "action": "click",
          "args": [ "EAImportantInfosConfirmationRead_0__Selected_radioButton_label", "" ]
        },
        {
          "action": "click",
          "args": [ "EAImportantInfosConfirmationAccountInfos_0__Selected_radioButton_label", "" ]
        },
        {
          "action": "click",
          "args": [ "Wizard_EAImportantNotifications_nextButton", "" ]
        },
        {
          "action": "click",
          "args": [ "buttonNext", "" ]
        }

      ]
    }


  ]




}